{"data":{"propertyOrder":{},"properties":{"name":{"name":"name","reference":"scalar","getter":false,"setter":false,"array":false},"description":{"name":"description","reference":"scalar","getter":false,"setter":false,"array":false,"optional":true},"flies":{"name":"flies","reference":"m:n","cascade":["persist"],"mappedBy":"imitatees","type":"Fly","fixedOrder":false,"array":false}},"props":[{"name":"name","reference":"scalar","getter":false,"setter":false,"array":false},{"name":"description","reference":"scalar","getter":false,"setter":false,"array":false,"optional":true},{"name":"flies","reference":"m:n","cascade":["persist"],"mappedBy":"imitatees","type":"Fly","fixedOrder":false,"array":false}],"primaryKeys":[],"filters":{},"hooks":{},"indexes":[],"uniques":[],"checks":[],"concurrencyCheckKeys":{},"className":"Imitatee","path":"./src/api/imitatee/imitatee.entity.ts","name":"Imitatee","abstract":false,"constructorParams":[],"toJsonParams":[],"extends":"BaseEntity","useCache":true,"relations":[{"name":"flies","reference":"m:n","cascade":["persist"],"mappedBy":"imitatees","type":"Fly","fixedOrder":false,"array":false}],"collection":"imitatee"},"origin":"./src/api/imitatee/imitatee.entity.ts","hash":"16fde16fe2f3d287ffec8777f7d2067d","version":"5.7.13"}
